toon_parse/__init__.py
toon_parse/async_converter.py
toon_parse/constants.py
toon_parse/csv_converter.py
toon_parse/encrypt.py
toon_parse/json_converter.py
toon_parse/utils.py
toon_parse/validator.py
toon_parse/xml_converter.py
toon_parse/yaml_converter.py
toon_parse/cli/__init__.py
toon_parse/csv_parse/__init__.py
toon_parse/csv_parse/async_converter.py
toon_parse/csv_parse/validator.py
toon_parse/json_parse/__init__.py
toon_parse/json_parse/async_converter.py
toon_parse/json_parse/csv_converter.py
toon_parse/json_parse/validator.py
toon_parse/json_parse/xml_converter.py
toon_parse/json_parse/yaml_converter.py
toon_parse/xml_parse/__init__.py
toon_parse/xml_parse/async_converter.py
toon_parse/xml_parse/csv_converter.py
toon_parse/xml_parse/validator.py
toon_parse/yaml_parse/__init__.py
toon_parse/yaml_parse/async_converter.py
toon_parse/yaml_parse/csv_converter.py
toon_parse/yaml_parse/validator.py
toon_parse/yaml_parse/xml_converter.py
toon_parse-2.4.4.dist-info/licenses/LICENSE
toon_parse-2.4.4.dist-info/METADATA
toon_parse-2.4.4.dist-info/WHEEL
toon_parse-2.4.4.dist-info/entry_points.txt
toon_parse-2.4.4.dist-info/top_level.txt
toon_parse-2.4.4.dist-info/RECORD
