Metadata-Version: 2.4
Name: toon-parse
Version: 2.4.4
Summary: A powerful context reduction tool centered around converting data (JSON, YAML, XML, CSV) to the token-optimized TOON format for efficient LLM interactions.
Author-email: Ankit Pal <ankitpal181@gmail.com>
Project-URL: Documentation, https://toonformatter.net/docs.html?package=toon-parse
Project-URL: Download, https://pypi.org/project/toon-parse/#files
Project-URL: Source, https://github.com/ankitpal181/toon-formatter-py
Project-URL: Bug Tracker, https://github.com/ankitpal181/toon-formatter-py/issues
Project-URL: Funding, https://github.com/sponsors/ankitpal181
Project-URL: POC Tool, https://toonformatter.net/
Classifier: Programming Language :: Python :: 3.10
Classifier: Programming Language :: Python :: 3.11
Classifier: Programming Language :: Python :: 3.12
Classifier: Programming Language :: Python :: 3.13
Classifier: Topic :: Software Development
Classifier: License :: OSI Approved :: MIT License
Classifier: Operating System :: OS Independent
Classifier: Intended Audience :: Developers
Classifier: Intended Audience :: Education
Classifier: Development Status :: 5 - Production/Stable
Requires-Python: >=3.10
License-File: LICENSE
Requires-Dist: PyYAML>=6.0
Requires-Dist: cryptography>=3.0
Dynamic: license-file
